gathers-0.3.1.dist-info/METADATA
gathers-0.3.1.dist-info/WHEEL
gathers.libs/libgcc_s-b5472b99.so.1
gathers/__init__.py
gathers/py.typed
gathers/gatherspy.abi3.so
gathers-0.3.1.dist-info/RECORD
